Metadata-Version: 2.1
Name: M3u8Viewer
Version: 0.0.1
Summary: Parse M3U8
Author: hebaodan
Author-email: 3594056838@qq.com
License: MIT
